{"frames": {

"FoodBud.png":
{
	"frame": {"x":48,"y":0,"w":16,"h":16},
	"rotated": false,
	"trimmed": false,
	"spriteSourceSize": {"x":0,"y":0,"w":16,"h":16},
	"sourceSize": {"w":16,"h":16}
},
"FoodEaten.png":
{
	"frame": {"x":32,"y":0,"w":16,"h":16},
	"rotated": false,
	"trimmed": false,
	"spriteSourceSize": {"x":0,"y":0,"w":16,"h":16},
	"sourceSize": {"w":16,"h":16}
},
"FoodRipe.png":
{
	"frame": {"x":0,"y":0,"w":16,"h":16},
	"rotated": false,
	"trimmed": false,
	"spriteSourceSize": {"x":0,"y":0,"w":16,"h":16},
	"sourceSize": {"w":16,"h":16}
},
"FoodRot.png":
{
	"frame": {"x":16,"y":0,"w":16,"h":16},
	"rotated": false,
	"trimmed": false,
	"spriteSourceSize": {"x":0,"y":0,"w":16,"h":16},
	"sourceSize": {"w":16,"h":16}
},
"GameOver.png":
{
	"frame": {"x":0,"y":73,"w":600,"h":600},
	"rotated": false,
	"trimmed": false,
	"spriteSourceSize": {"x":0,"y":0,"w":600,"h":600},
	"sourceSize": {"w":600,"h":600}
},
"GameTitle.png":
{
	"frame": {"x":0,"y":673,"w":600,"h":600},
	"rotated": false,
	"trimmed": false,
	"spriteSourceSize": {"x":0,"y":0,"w":600,"h":600},
	"sourceSize": {"w":600,"h":600}
},
"HelpButton.png":
{
	"frame": {"x":289,"y":0,"w":165,"h":73},
	"rotated": false,
	"trimmed": false,
	"spriteSourceSize": {"x":0,"y":0,"w":165,"h":73},
	"sourceSize": {"w":165,"h":73}
},
"PlayerBody.png":
{
	"frame": {"x":64,"y":0,"w":28,"h":24},
	"rotated": false,
	"trimmed": false,
	"spriteSourceSize": {"x":0,"y":0,"w":28,"h":24},
	"sourceSize": {"w":28,"h":24}
},
"PlayerLegs.png":
{
	"frame": {"x":92,"y":0,"w":32,"h":32},
	"rotated": false,
	"trimmed": false,
	"spriteSourceSize": {"x":0,"y":0,"w":32,"h":32},
	"sourceSize": {"w":32,"h":32}
},
"StartButton.png":
{
	"frame": {"x":124,"y":0,"w":165,"h":73},
	"rotated": false,
	"trimmed": false,
	"spriteSourceSize": {"x":0,"y":0,"w":165,"h":73},
	"sourceSize": {"w":165,"h":73}
}},
"meta": {
	"app": "https://www.codeandweb.com/texturepacker",
	"version": "1.0",
	"image": "GameAssets.png",
	"format": "RGBA8888",
	"size": {"w":600,"h":1273},
	"scale": "1",
	"smartupdate": "$TexturePacker:SmartUpdate:eb19e8b7afcf1c440bb3bd8d85a4fd93:8bcbcc6222ca991e5b9502b4f5c104ee:836ade03d2a078f61e02740e9d8035b0$"
}
}
